smarter/__about__.py
smarter/__init__.py
smarter/__version__.py
smarter/api/__init__.py
smarter/api/client.py
smarter/common/__init__.py
smarter/common/classes.py
smarter/common/conf.py
smarter/common/const.py
smarter/common/exceptions.py
smarter/common/mixins.py
smarter/common/utils.py
smarter/common/validators.py
smarter/common/models/__init__.py
smarter/common/models/base.py
smarter/common/models/whoami.py
smarter/resources/__init__.py
smarter/resources/account.py
smarter/resources/chatbot.py
smarter/resources/plugin.py
smarter/resources/models/__init__.py
smarter/resources/models/chatbot.py
smarter/resources/models/prompt.py
smarter/settings/__init__.py
smarter/settings/alpha.py
smarter/settings/base.py
smarter/settings/beta.py
smarter/settings/local.py
smarter/settings/prod.py
smarter/tests/__init__.py
smarter/tests/test_smarter.py
smarter_api-0.1.3.dist-info/licenses/LICENSE.txt
smarter_api-0.1.3.dist-info/METADATA
smarter_api-0.1.3.dist-info/WHEEL
smarter_api-0.1.3.dist-info/top_level.txt
smarter_api-0.1.3.dist-info/RECORD
