Metadata-Version: 2.4
Name: smarter-api
Version: 0.1.3
Summary: The official Python library for the Smarter platform Api.
Home-page: https://github.com/smarter-sh/smarter-python/
Author: Lawrence McDaniel
Author-email: lpm0073@gmail.com
Maintainer: Lawrence McDaniel
Maintainer-email: lpm0073@gmail.com
License: AGPL-3.0-or-later
Project-URL: Source, https://github.com/smarter-sh/smarter-python
Project-URL: Documentation, https://pypi.org/project/smarter-api/
Project-URL: Changelog, https://github.com/smarter-sh/smarter-python/blob/main/CHANGELOG.md
Project-URL: Security, https://github.com/smarter-sh/smarter-python/blob/main/SECURITY.md
Project-URL: Code of Conduct, https://github.com/smarter-sh/smarter-python/blob/main/CODE_OF_CONDUCT.md
Project-URL: Tracker, https://github.com/smarter-sh/smarter-python/issues
Keywords: api,smarter,ai
Platform: any
Classifier: Development Status :: 3 - Alpha
Classifier: Environment :: Console
Classifier: Intended Audience :: Developers
Classifier: Operating System :: OS Independent
Classifier: Programming Language :: Python
Classifier: Programming Language :: Python :: 3
Classifier: Programming Language :: Python :: 3 :: Only
Classifier: Programming Language :: Python :: 3.8
Classifier: Programming Language :: Python :: 3.9
Classifier: Programming Language :: Python :: 3.10
Classifier: Programming Language :: Python :: 3.11
Classifier: Programming Language :: Python :: 3.12
Classifier: Programming Language :: Python :: 3.13
Classifier: Programming Language :: Python :: Implementation :: PyPy
Classifier: Topic :: Utilities
Requires-Python: >=3.10
License-File: LICENSE.txt
Requires-Dist: setuptools==78.1.0
Requires-Dist: cachetools==5.5.2
Requires-Dist: httpx>=0.23.0
Requires-Dist: validators==0.34.0
Requires-Dist: email-validator==2.2.0
Requires-Dist: python-dotenv==1.1.0
Requires-Dist: pydantic>=2.0.0
Requires-Dist: pydantic-settings>=2.0.0
Requires-Dist: typing-extensions>=4.11
Dynamic: author
Dynamic: author-email
Dynamic: classifier
Dynamic: description
Dynamic: description-content-type
Dynamic: home-page
Dynamic: keywords
Dynamic: license
Dynamic: license-file
Dynamic: maintainer
Dynamic: maintainer-email
Dynamic: platform
Dynamic: project-url
Dynamic: requires-dist
Dynamic: requires-python
Dynamic: summary
